rotalabs_fieldmem/__init__.py
rotalabs_fieldmem/_version.py
rotalabs_fieldmem/agents/__init__.py
rotalabs_fieldmem/agents/collective.py
rotalabs_fieldmem/agents/coordinator.py
rotalabs_fieldmem/agents/coupling.py
rotalabs_fieldmem/agents/ftcs_agent.py
rotalabs_fieldmem/agents/multi_agent.py
rotalabs_fieldmem/fields/__init__.py
rotalabs_fieldmem/fields/memory_field.py
rotalabs_fieldmem/fields/operations.py
rotalabs_fieldmem/fields/optimized.py
rotalabs_fieldmem/fields/sparse.py
rotalabs_fieldmem/integrations/__init__.py
rotalabs_fieldmem/integrations/vertex_ai.py
rotalabs_fieldmem/memory/__init__.py
rotalabs_fieldmem/memory/consolidation.py
rotalabs_fieldmem/memory/forgetting.py
rotalabs_fieldmem/memory/importance.py
rotalabs_fieldmem/utils/__init__.py
rotalabs_fieldmem/utils/config.py
rotalabs_fieldmem/utils/embeddings.py
rotalabs_fieldmem/utils/metrics.py
rotalabs_fieldmem/utils/persistence.py
rotalabs_fieldmem/utils/schemas.py
rotalabs_fieldmem/viz/__init__.py
rotalabs_fieldmem/viz/plotting.py
rotalabs_fieldmem-1.0.0.dist-info/METADATA
rotalabs_fieldmem-1.0.0.dist-info/WHEEL
rotalabs_fieldmem-1.0.0.dist-info/licenses/LICENSE
rotalabs_fieldmem-1.0.0.dist-info/RECORD
