Metadata-Version: 2.4
Name: rotalabs-fieldmem
Version: 1.0.0
Summary: Field-Theoretic Memory System - PDE-based memory for AI agents with natural diffusion and thermodynamic forgetting
Project-URL: Homepage, https://rotalabs.ai
Project-URL: Repository, https://github.com/rotalabs/rotalabs-fieldmem
Project-URL: Documentation, https://rotalabs.github.io/rotalabs-fieldmem/
Author-email: Subhadip Mitra <subhadip@rotalabs.ai>, Rotalabs Research <research@rotalabs.ai>
License-Expression: AGPL-3.0-or-later
License-File: LICENSE
Keywords: agent-memory,ai-memory,collective-intelligence,field-theory,jax,pde,temporal-memory
Classifier: Development Status :: 4 - Beta
Classifier: Intended Audience :: Developers
Classifier: Intended Audience :: Science/Research
Classifier: License :: OSI Approved :: GNU Affero General Public License v3 or later (AGPLv3+)
Classifier: Programming Language :: Python :: 3
Classifier: Programming Language :: Python :: 3.9
Classifier: Programming Language :: Python :: 3.10
Classifier: Programming Language :: Python :: 3.11
Classifier: Programming Language :: Python :: 3.12
Classifier: Topic :: Scientific/Engineering :: Artificial Intelligence
Requires-Python: >=3.9
Requires-Dist: jax>=0.4.0
Requires-Dist: jaxlib>=0.4.0
Requires-Dist: numpy>=1.24.0
Requires-Dist: pyyaml>=6.0
Requires-Dist: scipy>=1.10.0
Provides-Extra: all
Requires-Dist: google-cloud-aiplatform>=1.38.0; extra == 'all'
Requires-Dist: google-generativeai>=0.3.0; extra == 'all'
Requires-Dist: matplotlib>=3.7.0; extra == 'all'
Requires-Dist: seaborn>=0.12.0; extra == 'all'
Requires-Dist: sentence-transformers>=2.2.0; extra == 'all'
Provides-Extra: dev
Requires-Dist: black>=23.0.0; extra == 'dev'
Requires-Dist: mypy>=1.5.0; extra == 'dev'
Requires-Dist: pytest-asyncio>=0.21.0; extra == 'dev'
Requires-Dist: pytest-cov>=4.1.0; extra == 'dev'
Requires-Dist: pytest>=7.4.0; extra == 'dev'
Requires-Dist: ruff>=0.1.0; extra == 'dev'
Provides-Extra: docs
Requires-Dist: mkdocs-material>=9.4.0; extra == 'docs'
Requires-Dist: mkdocs>=1.5.0; extra == 'docs'
Requires-Dist: mkdocstrings[python]>=0.24.0; extra == 'docs'
Provides-Extra: embeddings
Requires-Dist: sentence-transformers>=2.2.0; extra == 'embeddings'
Provides-Extra: gcp
Requires-Dist: google-cloud-aiplatform>=1.38.0; extra == 'gcp'
Requires-Dist: google-generativeai>=0.3.0; extra == 'gcp'
Provides-Extra: viz
Requires-Dist: matplotlib>=3.7.0; extra == 'viz'
Requires-Dist: seaborn>=0.12.0; extra == 'viz'
